converter/__init__.py
converter/main.py
converter_example_by_thuongnn_v1-0.1.0.dist-info/LICENSE
converter_example_by_thuongnn_v1-0.1.0.dist-info/METADATA
converter_example_by_thuongnn_v1-0.1.0.dist-info/WHEEL
converter_example_by_thuongnn_v1-0.1.0.dist-info/top_level.txt
converter_example_by_thuongnn_v1-0.1.0.dist-info/RECORD
