Metadata-Version: 2.1
Name: converter-example-by-thuongnn-v1
Version: 0.1.0
Summary: Sort description
Home-page: https://github.com/thuongnn/github-actions-learning-python.git
Author: Nguyen Nhu Thuong
Author-email: thuongnn@ssi.com.vn
License: UNKNOWN
Platform: UNKNOWN
Classifier: Programming Language :: Python :: 2
Classifier: License :: OSI Approved :: MIT License
Classifier: Operating System :: OS Independent
License-File: LICENSE
